libi/dataframes.py
libi/errors.py
libi/utils.py
cobli_libi-0.0.5.dist-info/METADATA
cobli_libi-0.0.5.dist-info/WHEEL
cobli_libi-0.0.5.dist-info/top_level.txt
cobli_libi-0.0.5.dist-info/RECORD
