Metadata-Version: 2.1
Name: cobli-libi
Version: 0.0.5
Summary: Generate dataframes from Cobli public API
Home-page: https://docs.cobli.co
Author: Marcus Beckenkamp
Author-email: mvbeck@gmai.com
